pyboom/__init__.py
pyboom/__main__.py
pyboom/pyboom.py
pyboom-0.4.0.dist-info/entry_points.txt
pyboom-0.4.0.dist-info/WHEEL
pyboom-0.4.0.dist-info/METADATA
pyboom-0.4.0.dist-info/RECORD
